gnomonicus/__init__.py
gnomonicus/gnomonicus_lib.py
gnomonicus-3.0.10.data/scripts/gnomonicus
gnomonicus-3.0.10.data/scripts/gnomonicus-table-update
gnomonicus-3.0.10.data/scripts/merge-vcfs
gnomonicus-3.0.10.dist-info/licenses/LICENSE
gnomonicus-3.0.10.dist-info/METADATA
gnomonicus-3.0.10.dist-info/WHEEL
gnomonicus-3.0.10.dist-info/top_level.txt
gnomonicus-3.0.10.dist-info/RECORD
