Metadata-Version: 2.4
Name: gnomonicus
Version: 3.0.10
Summary: Python code to integrate results of tb-pipeline and provide an antibiogram, mutations and variants
Home-page: https://github.com/oxfordmmm/gnomonicus
Author: Philip W Fowler, Jeremy Westhead
Author-email: philip.fowler@ndm.ox.ac.uk
License: University of Oxford License, see LICENSE
Keywords: gnomonicus,piezo,lodestone,clockwork,TB
Classifier: Programming Language :: Python :: 3
Requires-Python: >=3.10
License-File: LICENSE
Requires-Dist: bio-grumpy>=1.0.0
Requires-Dist: piezo>=0.9.1
Requires-Dist: vcf_subset>=2.0.0
Requires-Dist: numpy
Requires-Dist: pandas
Requires-Dist: tqdm
Requires-Dist: recursive_diff
Dynamic: license-file
